ombori/__init__.py
ombori/grid/__init__.py
ombori.grid-1.17.0.dist-info/METADATA
ombori.grid-1.17.0.dist-info/WHEEL
ombori.grid-1.17.0.dist-info/top_level.txt
ombori.grid-1.17.0.dist-info/RECORD
