Metadata-Version: 2.1
Name: ombori.grid
Version: 1.17.0
Requires-Python: >=3.6
Requires-Dist: paho-mqtt
